main.py
aionrails-0.2.3.dist-info/METADATA
aionrails-0.2.3.dist-info/WHEEL
aionrails-0.2.3.dist-info/top_level.txt
aionrails-0.2.3.dist-info/RECORD
