Metadata-Version: 2.4
Name: aionrails
Version: 0.2.3
Summary: A meta package for AI-on-Rails: A Python library for prototyping and publishing AI applications with guardrails.
Requires-Python: >=3.10
Requires-Dist: aor>=0.2.3
